{"about":"","calendar":{"1721403142":1,"1721403846":1,"1721404308":1,"1721404406":1,"1721404550":1,"1721404727":1,"1721404778":1,"1721404893":1,"1721404963":1,"1721405226":1,"1721405625":1,"1721405851":1,"1721406442":1,"1721406645":1,"1721406793":1,"1721407164":1,"1721407350":1,"1721408047":1,"1721408593":1,"1721408897":1,"1721408949":1,"1721409021":1,"1721409096":1,"1721409219":1,"1721409335":1,"1721409381":1,"1721409426":1,"1721409666":1,"1721409793":1,"1721409882":1,"1721409964":1,"1721410069":1},"completedChallenges":[{"id":"bad87fee1348bd9acde08712","completedDate":1721403846665,"challengeFiles":[]},{"id":"bad87fee1348bd9acde08812","completedDate":1721404308557,"challengeFiles":[]},{"id":"bad87fee1348bd9acde08812","completedDate":1721404308556,"challengeFiles":[]},{"id":"bad87fee1348bd8acde08812","completedDate":1721404406827,"challengeFiles":[]},{"id":"bad87fee1348cd8acdf08812","completedDate":1721404550030,"challengeFiles":[]},{"id":"bad87fee1348cd8acef08812","completedDate":1721404727366,"challengeFiles":[]},{"id":"bad87fee1348cd8acef08811","completedDate":1721404778320,"challengeFiles":[]},{"id":"bad87fee1348cd8acef08813","completedDate":1721404893985,"challengeFiles":[]},{"id":"bad87fee1348ce8acef08814","completedDate":1721404963912,"challengeFiles":[]},{"id":"bad88fee1348ce8acef08815","completedDate":1721405226947,"challengeFiles":[]},{"id":"bad87fee1347bd9aedf08845","completedDate":1721405625115,"challengeFiles":[]},{"id":"bad87fee1348bd9aedf08845","completedDate":1721405851895,"challengeFiles":[]},{"id":"bad87fee1348bd9aede08845","completedDate":1721406442338,"challengeFiles":[]},{"id":"bad87fee1348bd9aedd08845","completedDate":1721406645230,"challengeFiles":[]},{"id":"bad87fee1348bd9aedc08845","completedDate":1721406793317,"challengeFiles":[]},{"id":"bad87fee1348bd9aedb08845","completedDate":1721407164512,"challengeFiles":[]},{"id":"bad87fee1348bd9aeda08845","completedDate":1721407350668,"challengeFiles":[]},{"id":"bad87fee1348bd9aed908845","completedDate":1721408047515,"challengeFiles":[]},{"id":"bad87fee1348bd9aec908845","completedDate":1721408593346,"challengeFiles":[]},{"id":"bad87fee1348bd9aec908846","completedDate":1721408897580,"challengeFiles":[]},{"id":"bad87fee1348bd9aec908746","completedDate":1721408949496,"challengeFiles":[]},{"id":"bad87fee1348bd9bec908846","completedDate":1721409021558,"challengeFiles":[]},{"id":"bad87fee1348bd9aec908847","completedDate":1721409096211,"challengeFiles":[]},{"id":"bad87fee1348bd9aec908848","completedDate":1721409219085,"challengeFiles":[]},{"id":"bad87fee1348bd9aec908849","completedDate":1721409335543,"challengeFiles":[]},{"id":"bad87fee1348bd9aec908850","completedDate":1721409381461,"challengeFiles":[]},{"id":"bad87fee1348bd9aec908852","completedDate":1721409426729,"challengeFiles":[]},{"id":"bad87fee1348bd9aec908853","completedDate":1721409666962,"challengeFiles":[]},{"id":"bad87fee1348bd9aec908854","completedDate":1721409793059,"challengeFiles":[]},{"id":"bad87fee1348bd9aec908855","completedDate":1721409882983,"challengeFiles":[]},{"id":"bad87fee1348bd9aec908856","completedDate":1721409964656,"challengeFiles":[]},{"id":"bad87fee1348bd9aec908857","completedDate":1721410069582,"challengeFiles":[]}],"completedExams":[],"isApisMicroservicesCert":false,"isBackEndCert":false,"isCheater":false,"isDonating":false,"is2018DataVisCert":false,"isDataVisCert":false,"isFrontEndCert":false,"isFullStackCert":false,"isFrontEndLibsCert":false,"isHonest":false,"isInfosecQaCert":false,"isQaCertV7":false,"isInfosecCertV7":false,"isJsAlgoDataStructCert":false,"isRelationalDatabaseCertV8":false,"isRespWebDesignCert":false,"isSciCompPyCertV7":false,"isDataAnalysisPyCertV7":false,"isMachineLearningPyCertV7":false,"isCollegeAlgebraPyCertV8":false,"isFoundationalCSharpCertV8":false,"isJsAlgoDataStructCertV8":false,"location":"","name":"","partiallyCompletedChallenges":[],"points":33,"portfolio":[],"profileUI":{"isLocked":false,"showAbout":true,"showCerts":true,"showDonation":false,"showHeatMap":true,"showLocation":true,"showName":true,"showPoints":true,"showPortfolio":true,"showTimeLine":true},"savedChallenges":[],"username":"faisalnightstar","yearsTopContributor":[],"currentChallengeId":"","email":"a68823845@gmail.com","emailVerified":true,"id":"669a870694ae8ec46391411a","sendQuincyEmail":true,"theme":"night","keyboardShortcuts":true,"completedChallengeCount":32,"acceptedPrivacyTerms":true,"isEmailVerified":true,"picture":"","joinDate":"2024-07-19T15:32:22.000Z","completedSurveys":[],"sessionUser":true,"sound":true}